liquidSVM.pyd
liquidSVM/__init__.py
liquidSVM/__main__.py
liquidSVM/doc.py
liquidSVM/data/banana-bc.test.csv
liquidSVM/data/banana-bc.train.csv
liquidSVM/data/banana-mc.test.csv
liquidSVM/data/banana-mc.train.csv
liquidSVM/data/covtype.1000.test.csv
liquidSVM/data/covtype.1000.train.csv
liquidSVM/data/reg-1d.test.csv
liquidSVM/data/reg-1d.train.csv
liquidSVM-1.0.1.dist-info/DESCRIPTION.rst
liquidSVM-1.0.1.dist-info/METADATA
liquidSVM-1.0.1.dist-info/RECORD
liquidSVM-1.0.1.dist-info/WHEEL
liquidSVM-1.0.1.dist-info/metadata.json
liquidSVM-1.0.1.dist-info/top_level.txt
