Metadata-Version: 2.0
Name: liquidSVM
Version: 1.0.1
Summary: Support vector machines (SVMs) and related kernel-based learning
Home-page: http://www.isa.uni-stuttgart.de/software/
Author: Ingo Steinwart, Philipp Thomann
Author-email: philipp.thomann@mathematik.uni-stuttgart.de
License: AGPL v3
Platform: UNKNOWN
Requires-Dist: numpy
